LICENSE
MANIFEST.in
README.md
setup.py
rds_maker/__init__.py
rds_maker/rds_maker.py
rdsmaker.egg-info/PKG-INFO
rdsmaker.egg-info/SOURCES.txt
rdsmaker.egg-info/dependency_links.txt
rdsmaker.egg-info/top_level.txt