Metadata-Version: 1.0
Name: rdsmaker
Version: 0.1.0
Summary: thin wrapper boto3 for RDS.
Home-page: https://github.com/denzow/rds_maker
Author: denzow
Author-email: denzow@gmail.com
License: MIT License
